[{"Id":1, "Nombre":"", "NombreIng":"Deja Que Yo Te Cuente", "Interprete":"38 Cap\u00edtulos", "Origen":"Cuba", "Anno":2018, "Definicion":"", "Foto":"Deja Que Yo Te Cuento.JPG"},
 {"Id":2, "Nombre":"", "NombreIng":"Jorge Diaz", "Interprete":"11 Cap\u00edtulos", "Origen":"Cuba", "Anno":2018, "Definicion":"", "Foto":"Descargando A Lo Cubano.JPG"},
 {"Id":3, "Nombre":"", "NombreIng":"El Sal\u00f3n De La Risa", "Interprete":"12 Cap\u00edtulos", "Origen":"Cuba", "Anno":2018, "Definicion":"", "Foto":"El Salon De La Risa.JPG"},
 {"Id":5, "Nombre":"", "NombreIng":"Salir Por Techo", "Interprete":"19 Cap\u00edtulos", "Origen":"Cuba", "Anno":2018, "Definicion":"", "Foto":"Salir Por El Techo.JPG"},
 {"Id":6, "Nombre":"", "NombreIng":"Tres X Uno Es Tres", "Interprete":"10 Cap\u00edtulos", "Origen":"Cuba", "Anno":2018, "Definicion":"", "Foto":"Tres X Uno Es Tres.JPG"},
 {"Id":7, "Nombre":"", "NombreIng":"Vivir Del Cuento", "Interprete":"239 Cap\u00edtulos", "Origen":"Cuba", "Anno":2017, "Definicion":"", "Foto":"Vivir Del Cuento.JPG"},
 {"Id":9, "Nombre":"", "NombreIng":"Jura Decir La Verdad", "Interprete":"48 Cap\u00edtulos", "Origen":"Cuba", "Anno":2018, "Definicion":"", "Foto":"Jura Decir La Verdad.JPG"},
 {"Id":10, "Nombre":"", "NombreIng":"El Titi Y El Nene", "Interprete":"09 Cap\u00edtulos", "Origen":"Cuba", "Anno":2017, "Definicion":"", "Foto":"El Titi Y El Nene.JPG"},
 {"Id":11, "Nombre":"", "NombreIng":"Otto Ortiz", "Interprete":"Cap\u00edtulos 19", "Origen":"Cuba", "Anno":2018, "Definicion":"", "Foto":"Otto Ortiz.JPG"},
 {"Id":13, "Nombre":"", "NombreIng":"Espectaculo Panfilo - Monologo A Varadero", "Interprete":"Panfilo", "Origen":"Cuba", "Anno":2018, "Definicion":"", "Foto":"Panfilo - Monologo A Varadero.JPG"},
 {"Id":14, "Nombre":"", "NombreIng":"Robertico - Cubanos De Noche En El Malecon", "Interprete":"Robertico", "Origen":"Cuba", "Anno":2015, "Definicion":"", "Foto":"Robertico - Cubanos De Noche En El Malecon.JPG"},
 {"Id":15, "Nombre":"", "NombreIng":"A Otro Con Este Cuento", "Interprete":"80 Cap\u00edtulos", "Origen":"Cuba", "Anno":2006, "Definicion":"", "Foto":"Humor Cubano.jpg"},
 {"Id":16, "Nombre":"", "NombreIng":"Cabo Pantera", "Interprete":"05 Cap\u00edtulos", "Origen":"Cuba", "Anno":2018, "Definicion":"", "Foto":"Humor Cubano.jpg"},
 {"Id":17, "Nombre":"", "NombreIng":"Carlos Ruiz De La Tejera", "Interprete":"11 Cap\u00edtulos", "Origen":"Cuba", "Anno":2018, "Definicion":"", "Foto":"Humor Cubano.jpg"},
 {"Id":18, "Nombre":"", "NombreIng":"Churrisco", "Interprete":"02 Cap\u00edtulos", "Origen":"Cuba", "Anno":2018, "Definicion":"", "Foto":"Humor Cubano.jpg"},
 {"Id":19, "Nombre":"", "NombreIng":"En Humor A La Verdad", "Interprete":"12 Cap\u00edtulos", "Origen":"Cuba", "Anno":2018, "Definicion":"", "Foto":"Humor Cubano.jpg"},
 {"Id":20, "Nombre":"", "NombreIng":"Limay Blanco", "Interprete":"03 Cap\u00edtulos", "Origen":"Cuba", "Anno":2018, "Definicion":"", "Foto":"Humor Cubano.jpg"},
 {"Id":21, "Nombre":"", "NombreIng":"Mente De Pollo", "Interprete":"10 Cap\u00edtulos", "Origen":"Cuba", "Anno":2018, "Definicion":"", "Foto":"Humor Cubano.jpg"},
 {"Id":22, "Nombre":"", "NombreIng":"Pagola La Paga", "Interprete":"10 Cap\u00edtulos", "Origen":"Cuba", "Anno":2018, "Definicion":"", "Foto":"Humor Cubano.jpg"},
 {"Id":23, "Nombre":"", "NombreIng":"Punto G", "Interprete":"20 Cap\u00edtulos", "Origen":"Cuba", "Anno":2018, "Definicion":"", "Foto":"Punto G.jpg"},
 {"Id":24, "Nombre":"", "NombreIng":"Punto Y Coma", "Interprete":"05 Cap\u00edtulos", "Origen":"Cuba", "Anno":2018, "Definicion":"", "Foto":"Humor Cubano.jpg"},
 {"Id":25, "Nombre":"", "NombreIng":"Y T\u00fa De Qu\u00e9 Ee R\u00edes", "Interprete":"16 Cap\u00edtulos", "Origen":"Cuba", "Anno":2018, "Definicion":"", "Foto":"Humor Cubano.jpg"},
 {"Id":27, "Nombre":"", "NombreIng":"Omar Franco", "Interprete":"05 Capitulos", "Origen":"Cuba", "Anno":2018, "Definicion":"", "Foto":"Humor Cubano.jpg"},
 {"Id":29, "Nombre":"", "NombreIng":"Bajando Que Esta Nevando", "Interprete":"4 Capitulos", "Origen":"Cuba", "Anno":2019, "Definicion":"", "Foto":"Humor Cubano.jpg"},
 {"Id":30, "Nombre":"", "NombreIng":"Charlie Chaplin", "Interprete":"16 Cap\u00edtulos", "Origen":"Cuba", "Anno":0, "Definicion":"", "Foto":"Charlie Chaplin.JPG"},
 {"Id":31, "Nombre":"", "NombreIng":"Stan Laurel y Oliver Hardy", "Interprete":"11 Cap\u00edtulos", "Origen":"Cuba", "Anno":0, "Definicion":"", "Foto":"Stan Laurel y Oliver Hardy.JPG"},
 {"Id":32, "Nombre":"", "NombreIng":"Humor Cubano", "Interprete":"", "Origen":"Cuba", "Anno":2019, "Definicion":"", "Foto":"Humor Cubano 2019.jpg"},
 {"Id":33, "Nombre":"", "NombreIng":"Les Luthiers", "Interprete":"19 Capitulos", "Origen":"Cuba", "Anno":2019, "Definicion":"", "Foto":"NoImagen.png"},
 {"Id":34, "Nombre":"", "NombreIng":"No Quiero Llanto", "Interprete":"06 Capitulos", "Origen":"Cuba", "Anno":2019, "Definicion":"", "Foto":"Humor Cubano.jpg"},
 {"Id":35, "Nombre":"", "NombreIng":"Circuito Cerra -  Pateando La Lata", "Interprete":"28 Cap\u00edtulos", "Origen":"USA", "Anno":2019, "Definicion":"", "Foto":"Humor Cubano.jpg"},
 {"Id":36, "Nombre":"", "NombreIng":"La Llave", "Interprete":"06 Capitulos", "Origen":"USA", "Anno":2019, "Definicion":"", "Foto":"Humor Cubano.jpg"},
 {"Id":37, "Nombre":"", "NombreIng":"Agencia Empleadora - Antolin el Picho", "Interprete":"04 Capitulos", "Origen":"Cuba", "Anno":2020, "Definicion":"", "Foto":"Humor Cubano.jpg"},
 {"Id":38, "Nombre":"", "NombreIng":"Alegrias De sobre Mesa", "Interprete":"04 Capitulos", "Origen":"Cuba", "Anno":2020, "Definicion":"", "Foto":"Humor Cubano.jpg"},
 {"Id":39, "Nombre":"", "NombreIng":"Espectaculo Osvaldo Doimeadios - Aqui Cualquier", "Interprete":"Osvaldo Doimeadios", "Origen":"Cuba", "Anno":2020, "Definicion":"Full-HD", "Foto":"Osvaldo Doimeadios - Aqui Cualquier.jpg"},
 {"Id":40, "Nombre":"", "NombreIng":"Espectaculo Buena Risa Social Club", "Interprete":"", "Origen":"Cuba", "Anno":2016, "Definicion":"", "Foto":"Humor Cubano.jpg"},
 {"Id":41, "Nombre":"", "NombreIng":"Espectaculo Cuando Rigo Sue\u00f1a", "Interprete":"", "Origen":"Cuba", "Anno":2016, "Definicion":"", "Foto":"Humor Cubano.jpg"},
 {"Id":42, "Nombre":"", "NombreIng":"Espectaculo Locos En La Habana", "Interprete":"", "Origen":"Cuba", "Anno":2020, "Definicion":"", "Foto":"Locos En La Habana.JPG"},
 {"Id":43, "Nombre":"", "NombreIng":"Diverso Humor Cubano", "Interprete":"56 Capitulos", "Origen":"Cuba", "Anno":0, "Definicion":"", "Foto":"Humor Cubano.jpg"},
 {"Id":44, "Nombre":"", "NombreIng":"Los Roper", "Interprete":"03 Capitulos", "Origen":"Cuba", "Anno":2020, "Definicion":"", "Foto":"Humor Cubano.jpg"},
 {"Id":45, "Nombre":"", "NombreIng":"Espectaculo La Le\u00f1a Del Humor", "Interprete":"", "Origen":"Cuba", "Anno":2015, "Definicion":"Full-HD", "Foto":"Humor Cubano.jpg"},
 {"Id":46, "Nombre":"", "NombreIng":"Espectaculo  La Llave Y El Grupo Kom", "Interprete":"", "Origen":"Cuba", "Anno":2019, "Definicion":"", "Foto":"Humor Cubano.jpg"},
 {"Id":47, "Nombre":"Espectaculo La Creacion Del Mundo", "NombreIng":"", "Interprete":"", "Origen":"Cuba", "Anno":2013, "Definicion":"", "Foto":"Humor Cubano.jpg"}]